leap/__init__.py
leap/latex_ops.py
leap/leap.py
leap/fonts/Raleway-Italic.ttf
leap/fonts/Raleway-Italic.ttf:Zone.Identifier
leap/fonts/Raleway-Light.ttf
leap/fonts/Raleway-Light.ttf:Zone.Identifier
leap/fonts/Raleway-Medium.ttf
leap/fonts/Raleway-Medium.ttf:Zone.Identifier
leap/templates/classic/classic.cls
leap/templates/classic/resume.tex.jinja
leap/templates/minimal/minimal.cls
leap/templates/minimal/resume.tex.jinja
leap/templates/modern/modern.cls
leap/templates/modern/resume.tex.jinja
Leap_CV-1.3.dist-info/METADATA
Leap_CV-1.3.dist-info/WHEEL
Leap_CV-1.3.dist-info/entry_points.txt
Leap_CV-1.3.dist-info/top_level.txt
Leap_CV-1.3.dist-info/RECORD
