Metadata-Version: 2.1
Name: Leap-CV
Version: 1.3
Summary: Cv Generation Package
Author: 10 Academy
Requires-Dist: requests
Requires-Dist: jinja2
